NightPy
